EduCDM/__init__.py
EduCDM/meta.py
EduCDM/DINA/__init__.py
EduCDM/DINA/EM/DINA.py
EduCDM/DINA/EM/__init__.py
EduCDM/DINA/GD/DINA.py
EduCDM/DINA/GD/__init__.py
EduCDM/FuzzyCDF/FuzzyCDF.py
EduCDM/FuzzyCDF/__init__.py
EduCDM/FuzzyCDF/modules.py
EduCDM/ICD/ICD.py
EduCDM/ICD/__init__.py
EduCDM/ICD/utils.py
EduCDM/ICD/etl/__init__.py
EduCDM/ICD/etl/etl.py
EduCDM/ICD/etl/utils.py
EduCDM/ICD/metrics/__init__.py
EduCDM/ICD/metrics/metrics.py
EduCDM/ICD/sym/__init__.py
EduCDM/ICD/sym/fit_eval.py
EduCDM/ICD/sym/pos_linear.py
EduCDM/ICD/sym/net/__init__.py
EduCDM/ICD/sym/net/dtn.py
EduCDM/ICD/sym/net/mirt.py
EduCDM/ICD/sym/net/ncd.py
EduCDM/ICD/sym/net/net.py
EduCDM/IRR/DINA.py
EduCDM/IRR/IRT.py
EduCDM/IRR/MIRT.py
EduCDM/IRR/NCDM.py
EduCDM/IRR/__init__.py
EduCDM/IRR/loss.py
EduCDM/IRR/etl/__init__.py
EduCDM/IRR/etl/pair_etl.py
EduCDM/IRR/etl/point_etl.py
EduCDM/IRR/etl/utils.py
EduCDM/IRT/__init__.py
EduCDM/IRT/irt.py
EduCDM/IRT/EM/IRT.py
EduCDM/IRT/EM/__init__.py
EduCDM/IRT/GD/IRT.py
EduCDM/IRT/GD/__init__.py
EduCDM/KaNCD/KaNCD.py
EduCDM/KaNCD/__init__.py
EduCDM/MCD/MCD.py
EduCDM/MCD/__init__.py
EduCDM/MIRT/MIRT.py
EduCDM/MIRT/__init__.py
EduCDM/NCDM/NCDM.py
EduCDM/NCDM/__init__.py
tests/__init__.py
tests/dina/__init__.py
tests/dina/em/__init__.py
tests/dina/em/conftest.py
tests/dina/em/test_dina.py
tests/dina/gd/__init__.py
tests/dina/gd/conftest.py
tests/dina/gd/test_gddina.py
tests/fuzzycdf/__init__.py
tests/fuzzycdf/conftest.py
tests/fuzzycdf/test_fuzzycdf.py
tests/icd/__init__.py
tests/icd/conftest.py
tests/icd/test_mirt.py
tests/icd/test_ncd.py
tests/irr/__init__.py
tests/irr/conftest.py
tests/irr/test_dina.py
tests/irr/test_irt.py
tests/irr/test_mirt.py
tests/irr/test_ncdm.py
tests/irt/__init__.py
tests/irt/em/__init__.py
tests/irt/em/conftest.py
tests/irt/em/test_emirt.py
tests/irt/gd/__init__.py
tests/irt/gd/conftest.py
tests/irt/gd/test_gdirt.py
tests/kancd/__init__.py
tests/kancd/conftest.py
tests/kancd/test_kancd.py
tests/mcd/__init__.py
tests/mcd/conftest.py
EduCDM-1.0.1.dist-info/AUTHORS.md
EduCDM-1.0.1.dist-info/LICENSE
EduCDM-1.0.1.dist-info/METADATA
EduCDM-1.0.1.dist-info/WHEEL
EduCDM-1.0.1.dist-info/top_level.txt
EduCDM-1.0.1.dist-info/RECORD
