Metadata-Version: 2.1
Name: EduCDM
Version: 1.0.1
License-File: LICENSE
License-File: AUTHORS.md
Requires-Dist: torch
Requires-Dist: tqdm
Requires-Dist: numpy>=1.16.5
Requires-Dist: scikit-learn
Requires-Dist: pandas
Requires-Dist: longling>=1.3.33
Requires-Dist: longling<=1.3.36
Requires-Dist: PyBaize>=0.0.7
Requires-Dist: fire
Provides-Extra: test
Requires-Dist: pytest>=4; extra == "test"
Requires-Dist: pytest-cov>=2.6.0; extra == "test"
Requires-Dist: pytest-flake8<1.1.2; extra == "test"
Requires-Dist: flake8<5.0.0; extra == "test"
